jcvi/__init__.py
jcvi/_version.py
jcvi/cli.py
jcvi/algorithms/__init__.py
jcvi/algorithms/__main__.py
jcvi/algorithms/ec.py
jcvi/algorithms/formula.py
jcvi/algorithms/graph.py
jcvi/algorithms/lis.py
jcvi/algorithms/lpsolve.py
jcvi/algorithms/matrix.py
jcvi/algorithms/maxsum.py
jcvi/algorithms/supermap.py
jcvi/algorithms/tsp.py
jcvi/annotation/__init__.py
jcvi/annotation/__main__.py
jcvi/annotation/ahrd.py
jcvi/annotation/automaton.py
jcvi/annotation/depth.py
jcvi/annotation/evm.py
jcvi/annotation/maker.py
jcvi/annotation/pasa.py
jcvi/annotation/qc.py
jcvi/annotation/reformat.py
jcvi/annotation/stats.py
jcvi/annotation/train.py
jcvi/annotation/trinity.py
jcvi/apps/__init__.py
jcvi/apps/__main__.py
jcvi/apps/align.py
jcvi/apps/base.py
jcvi/apps/biomart.py
jcvi/apps/blastplus.py
jcvi/apps/bowtie.py
jcvi/apps/bwa.py
jcvi/apps/cdhit.py
jcvi/apps/emboss.py
jcvi/apps/fetch.py
jcvi/apps/gbsubmit.py
jcvi/apps/gmap.py
jcvi/apps/grid.py
jcvi/apps/lastz.py
jcvi/apps/mask.py
jcvi/apps/phylo.py
jcvi/apps/r.py
jcvi/apps/restriction.py
jcvi/apps/softlink.py
jcvi/apps/uclust.py
jcvi/apps/uniprot.py
jcvi/apps/vecscreen.py
jcvi/apps/wga2ribbon.py
jcvi/assembly/__init__.py
jcvi/assembly/__main__.py
jcvi/assembly/allmaps.py
jcvi/assembly/allpaths.py
jcvi/assembly/automaton.py
jcvi/assembly/base.py
jcvi/assembly/chic.c
jcvi/assembly/chic.cpython-310-darwin.so
jcvi/assembly/chic.cpython-312-darwin.so
jcvi/assembly/chic.pyx
jcvi/assembly/coverage.py
jcvi/assembly/gaps.py
jcvi/assembly/geneticmap.py
jcvi/assembly/goldenpath.py
jcvi/assembly/hic.py
jcvi/assembly/kmer.py
jcvi/assembly/opticalmap.py
jcvi/assembly/patch.py
jcvi/assembly/postprocess.py
jcvi/assembly/preprocess.py
jcvi/assembly/sim.py
jcvi/assembly/soap.py
jcvi/assembly/syntenypath.py
jcvi/compara/__init__.py
jcvi/compara/__main__.py
jcvi/compara/base.py
jcvi/compara/blastfilter.py
jcvi/compara/catalog.py
jcvi/compara/fractionation.py
jcvi/compara/ks.py
jcvi/compara/pad.py
jcvi/compara/pedigree.py
jcvi/compara/phylogeny.py
jcvi-1.5.11.dist-info/METADATA
jcvi-1.5.11.dist-info/WHEEL
jcvi-1.5.11.dist-info/entry_points.txt
jcvi-1.5.11.dist-info/licenses/LICENSE
jcvi-1.5.11.dist-info/RECORD
