Metadata-Version: 2.4
Name: jcvi
Version: 1.5.11
Summary: Python utility libraries on genome assembly, annotation and comparative genomics
Project-URL: homepage, http://github.com/tanghaibao/jcvi
Author: Vivek Krishnakumar, Adam Taranto
Author-email: Haibao Tang <tanghaibao@gmail.com>
License-Expression: BSD-3-Clause
License-File: LICENSE
Classifier: Intended Audience :: Science/Research
Classifier: Programming Language :: Python
Classifier: Programming Language :: Python :: 3
Classifier: Topic :: Scientific/Engineering :: Bio-Informatics
Requires-Python: <3.13,>=3.8
Requires-Dist: biopython
Requires-Dist: boto3
Requires-Dist: brewer2mpl
Requires-Dist: crossmap
Requires-Dist: cython
Requires-Dist: deap
Requires-Dist: ete3
Requires-Dist: ftpretty
Requires-Dist: genomepy
Requires-Dist: gffutils
Requires-Dist: goatools
Requires-Dist: graphviz
Requires-Dist: jinja2
Requires-Dist: matplotlib
Requires-Dist: more-itertools
Requires-Dist: natsort
Requires-Dist: networkx
Requires-Dist: numpy
Requires-Dist: ortools
Requires-Dist: pybedtools
Requires-Dist: pyefd
Requires-Dist: pypdf
Requires-Dist: pysam
Requires-Dist: pytesseract
Requires-Dist: rich
Requires-Dist: scikit-image
Requires-Dist: scipy
Requires-Dist: seaborn
Requires-Dist: wand
Requires-Dist: webcolors
Provides-Extra: tests
Requires-Dist: black; extra == 'tests'
Requires-Dist: hatch; extra == 'tests'
Requires-Dist: isort; extra == 'tests'
Requires-Dist: mock; extra == 'tests'
Requires-Dist: numpydoc-validation; extra == 'tests'
Requires-Dist: pre-commit; extra == 'tests'
Requires-Dist: pymdown-extensions; extra == 'tests'
Requires-Dist: pytest; extra == 'tests'
Requires-Dist: pytest-benchmark; extra == 'tests'
Requires-Dist: pytest-cov; extra == 'tests'
Requires-Dist: pyyaml; extra == 'tests'
